pyreqwest_impersonate-0.5.3.dist-info/METADATA
pyreqwest_impersonate-0.5.3.dist-info/WHEEL
pyreqwest_impersonate/__init__.py
pyreqwest_impersonate/pyreqwest_impersonate.abi3.so
pyreqwest_impersonate-0.5.3.dist-info/RECORD
